electriflux/polars_reader.py
electriflux/simple_flux.yaml
electriflux/simple_reader.py
electriflux/utils.py
electriflux-1.3.0.dist-info/LICENSE
electriflux-1.3.0.dist-info/METADATA
electriflux-1.3.0.dist-info/WHEEL
electriflux-1.3.0.dist-info/RECORD
