Metadata-Version: 2.3
Name: electriflux
Version: 1.3.0
Summary: Outils de lecture/écriture des flux
License: GPLv3
Author: Virgile Daugé
Author-email: virgile.dauge@pm.me
Requires-Python: >=3.10,<4.0
Classifier: License :: Other/Proprietary License
Classifier: Programming Language :: Python :: 3
Classifier: Programming Language :: Python :: 3.10
Classifier: Programming Language :: Python :: 3.11
Classifier: Programming Language :: Python :: 3.12
Classifier: Programming Language :: Python :: 3.13
Requires-Dist: lxml (>=5.3.0,<6.0.0)
Requires-Dist: pandas (>=2.2.3,<3.0.0)
Requires-Dist: paramiko (>=3.5.0,<4.0.0)
Requires-Dist: polars (>=1.21.0,<2.0.0)
Requires-Dist: pycryptodome (>=3.21.0,<4.0.0)
Requires-Dist: pyyaml (>=6.0.2,<7.0.0)
Project-URL: Homepage, https://github.com/Energie-De-Nantes/electriflux
Project-URL: Repository, https://github.com/Energie-De-Nantes/electriflux
